django_datatables_view/__init__.py
django_datatables_view/base_datatable_view.py
django_datatables_view/mixins.py
django_datatables_view-1.20.0.dist-info/LICENSE
django_datatables_view-1.20.0.dist-info/METADATA
django_datatables_view-1.20.0.dist-info/WHEEL
django_datatables_view-1.20.0.dist-info/top_level.txt
django_datatables_view-1.20.0.dist-info/RECORD
