Metadata-Version: 2.1
Name: django-datatables-view
Version: 1.20.0
Summary: Django datatables view
Home-page: https://bitbucket.org/pigletto/django-datatables-view
Author: Maciej Wiśniowski
Author-email: pigletto@gmail.com
License: MIT
Project-URL: Bug Tracker, https://bitbucket.org/pigletto/django-datatables-view/issues
Keywords: django,datatables
Platform: UNKNOWN
Classifier: Environment :: Web Environment
Classifier: Framework :: Django
Classifier: Development Status :: 5 - Production/Stable
Classifier: Programming Language :: Python :: 3
Classifier: License :: OSI Approved :: MIT License
Classifier: Operating System :: OS Independent
Requires-Python: >=3.6
License-File: LICENSE
